rpa_dates/__init__.py
rpa_dates/config.py
rpa_dates/exceptions.py
rpa_dates/factories.py
rpa_dates/interfaces.py
rpa_dates/service.py
rpa_dates/providers/__init__.py
rpa_dates/providers/fallback.py
rpa_dates/providers/holiday.py
rpa_dates/providers/nager_date_v3.py
rpa_dates/providers/nager_date_v4.py
rpa_dates/providers/open_holidays.py
rpa_dates-2.0.0.dist-info/METADATA
rpa_dates-2.0.0.dist-info/WHEEL
rpa_dates-2.0.0.dist-info/licenses/LICENSE
rpa_dates-2.0.0.dist-info/RECORD
