Metadata-Version: 2.4
Name: rpa-dates
Version: 2.0.0
Summary: Dates actions for RPA
Author-email: Grzegorz Zioło <kontakt@ziolo.be>
License-Expression: MIT
License-File: LICENSE
Keywords: business-days,dates,datetime,holidays
Requires-Python: >=3.10
Requires-Dist: holidays>=0.89
Requires-Dist: pytest>=9.0.2
Requires-Dist: python-dateutil>=2.8.2
Requires-Dist: requests>=2.31.0
